pytorch_essentials/__init__.py
pytorch_essentials/callbacks.py
pytorch_essentials/engine.py
pytorch_essentials/utils.py
pytorch_essentials/visualization.py
pytorch_essentials-0.1.1.dist-info/licenses/LICENSE
pytorch_essentials-0.1.1.dist-info/METADATA
pytorch_essentials-0.1.1.dist-info/WHEEL
pytorch_essentials-0.1.1.dist-info/top_level.txt
pytorch_essentials-0.1.1.dist-info/RECORD
