Metadata-Version: 2.4
Name: pytorch-essentials
Version: 0.1.1
Summary: PyTorch training utilities
Requires-Python: >=3.8
License-File: LICENSE
Requires-Dist: torch>=2.0.0
Requires-Dist: torchvision>=0.15.0
Requires-Dist: tqdm>=4.65.0
Requires-Dist: scikit-learn>=1.3.0
Requires-Dist: matplotlib>=3.7.0
Requires-Dist: PyYAML>=6.0
Requires-Dist: wandb>=0.15.0
Dynamic: license-file
